sccb/__init__.py
sccb/cli.py
sccb-0.4.3.dist-info/licenses/LICENSE
sccb-0.4.3.dist-info/METADATA
sccb-0.4.3.dist-info/WHEEL
sccb-0.4.3.dist-info/entry_points.txt
sccb-0.4.3.dist-info/top_level.txt
sccb-0.4.3.dist-info/RECORD
