Metadata-Version: 2.4
Name: sccb
Version: 0.4.3
Summary: SCCB – A customizable CLI tool for managing command shortcuts and clipboard snippets.
Author-email: Ajinkya Dhamdhere <aj.dhamdhere@gmail.com>
License-Expression: MIT
Project-URL: Homepage, https://github.com/Jinkuman/sccb
Project-URL: Source, https://github.com/Jinkuman/sccb
Project-URL: Bug Tracker, https://github.com/Jinkuman/sccb/issues
Keywords: cli,productivity,shortcuts,snippets,developer-tools
Classifier: Programming Language :: Python :: 3
Classifier: Operating System :: OS Independent
Classifier: Topic :: Utilities
Classifier: Topic :: Software Development :: Build Tools
Requires-Python: >=3.8
License-File: LICENSE
Requires-Dist: typer>=0.9.0
Requires-Dist: pyperclip>=1.8.0
Requires-Dist: rich>=13.0.0
Dynamic: license-file
